[
  {
    "UserName": "Gordon",
    "Email": "gordonwhitehead@codax.com",
    "Password": "password",
    "Gender": "male",
    "Joined": "2016-07-29T07:08:47 -06:00",
    "Adrs_Local": "Delmonico Place",
    "Adrs_City": "Bergoo",
    "Adrs_Division": "Iowa",
    "Adrs_Country": "Micronesia",
    "phone": "+880 (983) 491-2850"
  },
  {
    "UserName": "Shepherd",
    "Email": "shepherdwhitehead@codax.com",
    "Password": "password",
    "Gender": "male",
    "Joined": "2020-04-24T12:35:18 -06:00",
    "Adrs_Local": "Milford Street",
    "Adrs_City": "Davenport",
    "Adrs_Division": "Wyoming",
    "Adrs_Country": "Mayotte",
    "phone": "+880 (882) 559-2701"
  },
  {
    "UserName": "White",
    "Email": "whitewhitehead@codax.com",
    "Password": "password",
    "Gender": "male",
    "Joined": "2019-12-21T12:46:27 -06:00",
    "Adrs_Local": "Christopher Avenue",
    "Adrs_City": "Bowie",
    "Adrs_Division": "Nevada",
    "Adrs_Country": "Korea (South)",
    "phone": "+880 (902) 409-2775"
  },
  {
    "UserName": "Lela",
    "Email": "lelawhitehead@codax.com",
    "Password": "password",
    "Gender": "female",
    "Joined": "2018-06-11T01:52:49 -06:00",
    "Adrs_Local": "Ivan Court",
    "Adrs_City": "Bradenville",
    "Adrs_Division": "West Virginia",
    "Adrs_Country": "Pakistan",
    "phone": "+880 (921) 507-3047"
  },
  {
    "UserName": "Ferrell",
    "Email": "ferrellwhitehead@codax.com",
    "Password": "password",
    "Gender": "male",
    "Joined": "2014-10-01T03:27:35 -06:00",
    "Adrs_Local": "Furman Avenue",
    "Adrs_City": "Grimsley",
    "Adrs_Division": "Hawaii",
    "Adrs_Country": "St. Pierre and Miquelon",
    "phone": "+880 (933) 523-3275"
  },
  {
    "UserName": "Soto",
    "Email": "sotowhitehead@codax.com",
    "Password": "password",
    "Gender": "male",
    "Joined": "2019-04-26T06:45:15 -06:00",
    "Adrs_Local": "Glendale Court",
    "Adrs_City": "Wollochet",
    "Adrs_Division": "Maine",
    "Adrs_Country": "Brazil",
    "phone": "+880 (807) 479-2144"
  },
  {
    "UserName": "Rivas",
    "Email": "rivaswhitehead@codax.com",
    "Password": "password",
    "Gender": "male",
    "Joined": "2015-11-24T03:20:37 -06:00",
    "Adrs_Local": "Gates Avenue",
    "Adrs_City": "Cassel",
    "Adrs_Division": "Minnesota",
    "Adrs_Country": "Martinique",
    "phone": "+880 (948) 486-2322"
  },
  {
    "UserName": "Mercer",
    "Email": "mercerwhitehead@codax.com",
    "Password": "password",
    "Gender": "male",
    "Joined": "2020-03-25T06:30:36 -06:00",
    "Adrs_Local": "McKibbin Street",
    "Adrs_City": "Kennedyville",
    "Adrs_Division": "Rhode Island",
    "Adrs_Country": "Norfolk Island",
    "phone": "+880 (886) 497-2586"
  },
  {
    "UserName": "Fischer",
    "Email": "fischerwhitehead@codax.com",
    "Password": "password",
    "Gender": "male",
    "Joined": "2015-06-29T02:21:59 -06:00",
    "Adrs_Local": "Truxton Street",
    "Adrs_City": "Bellfountain",
    "Adrs_Division": "Federated States Of Micronesia",
    "Adrs_Country": "France, Metropolitan",
    "phone": "+880 (977) 423-3326"
  },
  {
    "UserName": "Nixon",
    "Email": "nixonwhitehead@codax.com",
    "Password": "password",
    "Gender": "male",
    "Joined": "2016-08-12T12:39:15 -06:00",
    "Adrs_Local": "Junius Street",
    "Adrs_City": "Cartwright",
    "Adrs_Division": "Massachusetts",
    "Adrs_Country": "S. Georgia and S. Sandwich Isls.",
    "phone": "+880 (898) 532-2787"
  },
  {
    "UserName": "Hilary",
    "Email": "hilarywhitehead@codax.com",
    "Password": "password",
    "Gender": "female",
    "Joined": "2014-01-24T05:40:46 -06:00",
    "Adrs_Local": "Remsen Street",
    "Adrs_City": "Turah",
    "Adrs_Division": "District Of Columbia",
    "Adrs_Country": "Ghana",
    "phone": "+880 (842) 421-3917"
  },
  {
    "UserName": "Estella",
    "Email": "estellawhitehead@codax.com",
    "Password": "password",
    "Gender": "female",
    "Joined": "2016-04-03T02:48:42 -06:00",
    "Adrs_Local": "Colby Court",
    "Adrs_City": "Cresaptown",
    "Adrs_Division": "Marshall Islands",
    "Adrs_Country": "Yugoslavia",
    "phone": "+880 (917) 566-3578"
  },
  {
    "UserName": "Essie",
    "Email": "essiewhitehead@codax.com",
    "Password": "password",
    "Gender": "female",
    "Joined": "2015-05-18T04:03:16 -06:00",
    "Adrs_Local": "Wilson Avenue",
    "Adrs_City": "Wintersburg",
    "Adrs_Division": "South Carolina",
    "Adrs_Country": "Kazakhstan",
    "phone": "+880 (838) 540-2189"
  },
  {
    "UserName": "Baxter",
    "Email": "baxterwhitehead@codax.com",
    "Password": "password",
    "Gender": "male",
    "Joined": "2016-06-03T02:35:20 -06:00",
    "Adrs_Local": "Rugby Road",
    "Adrs_City": "Conestoga",
    "Adrs_Division": "Idaho",
    "Adrs_Country": "Hong Kong",
    "phone": "+880 (821) 529-3873"
  },
  {
    "UserName": "Lauren",
    "Email": "laurenwhitehead@codax.com",
    "Password": "password",
    "Gender": "female",
    "Joined": "2019-03-12T12:19:36 -06:00",
    "Adrs_Local": "Garden Place",
    "Adrs_City": "Lodoga",
    "Adrs_Division": "Alabama",
    "Adrs_Country": "Malta",
    "phone": "+880 (888) 463-3445"
  },
  {
    "UserName": "Pope",
    "Email": "popewhitehead@codax.com",
    "Password": "password",
    "Gender": "male",
    "Joined": "2016-05-22T05:37:34 -06:00",
    "Adrs_Local": "Pulaski Street",
    "Adrs_City": "Roeville",
    "Adrs_Division": "Louisiana",
    "Adrs_Country": "Iceland",
    "phone": "+880 (993) 533-3200"
  },
  {
    "UserName": "Ericka",
    "Email": "erickawhitehead@codax.com",
    "Password": "password",
    "Gender": "female",
    "Joined": "2014-01-29T10:45:45 -06:00",
    "Adrs_Local": "Jerome Avenue",
    "Adrs_City": "Logan",
    "Adrs_Division": "Arizona",
    "Adrs_Country": "Guyana",
    "phone": "+880 (898) 495-3138"
  },
  {
    "UserName": "Suzette",
    "Email": "suzettewhitehead@codax.com",
    "Password": "password",
    "Gender": "female",
    "Joined": "2015-05-11T11:19:04 -06:00",
    "Adrs_Local": "Dunne Place",
    "Adrs_City": "Crucible",
    "Adrs_Division": "North Carolina",
    "Adrs_Country": "Libya",
    "phone": "+880 (907) 464-3172"
  }
]